xlrd3/__init__.py
xlrd3/biffh.py
xlrd3/book.py
xlrd3/compdoc.py
xlrd3/formatting.py
xlrd3/formula.py
xlrd3/info.py
xlrd3/sheet.py
xlrd3/timemachine.py
xlrd3/xldate.py
xlrd3/xlsx.py
xlrd3-1.1.0.data/scripts/runxlrd.py
xlrd3-1.1.0.dist-info/LICENSE
xlrd3-1.1.0.dist-info/METADATA
xlrd3-1.1.0.dist-info/WHEEL
xlrd3-1.1.0.dist-info/top_level.txt
xlrd3-1.1.0.dist-info/RECORD
