Metadata-Version: 2.1
Name: xlrd3
Version: 1.1.0
Summary: Library for developers to extract data from Microsoft Excel (tm) spreadsheet files
Home-page: https://github.com/Dragon2fly/xlrd3
Author: John Machin
Author-email: sjmachin@lexicon.net
Maintainer: Nguyen Ba Duc Tin
Maintainer-email: nguyenbaduc.tin@gmail.com
License: BSD
Keywords: xls,xlsx,excel,spreadsheet,workbook
Platform: Any platform -- don't need Windows
Classifier: Development Status :: 5 - Production/Stable
Classifier: Intended Audience :: Developers
Classifier: License :: OSI Approved :: BSD License
Classifier: Programming Language :: Python
Classifier: Programming Language :: Python :: 3.6
Classifier: Programming Language :: Python :: 3.7
Classifier: Programming Language :: Python :: 3.8
Classifier: Programming Language :: Python :: 3.9
Classifier: Operating System :: OS Independent
Classifier: Topic :: Database
Classifier: Topic :: Office/Business
Classifier: Topic :: Software Development :: Libraries :: Python Modules
Requires-Python: >=3.6
